{
"type": "FeatureCollection",
"name": "GarduListrik",
"crs": { "type": "name", "properties": { "name": "urn:ogc:def:crs:OGC:1.3:CRS84" } },
"features": [
{ "type": "Feature", "properties": { "NAMOBJ": "Gardu Induk Gedongpakuon", "JGLGRL": 1, "FCODE": null, "REMARK": "Gardu Induk", "SRS_ID": null, "LCODE": "HB0020", "METADATA": null }, "geometry": { "type": "Point", "coordinates": [ 105.253418048000071, -5.439355334999959, 193.0 ] } },
{ "type": "Feature", "properties": { "NAMOBJ": "Gardu Induk PLN Sukarame", "JGLGRL": 1, "FCODE": null, "REMARK": "Gardu Induk", "SRS_ID": null, "LCODE": "HB0020", "METADATA": null }, "geometry": { "type": "Point", "coordinates": [ 105.305194405000066, -5.362670636999951, 120.701000000000931 ] } }
]
}
